mdx_breakless_lists/__init__.py
mdx_breakless_lists/mdx_breakless_lists.py
mdx_breakless_lists/tests.py
mdx_breakless_lists/tt.py
mdx_breakless_lists-1.0.1.dist-info/LICENSE
mdx_breakless_lists-1.0.1.dist-info/METADATA
mdx_breakless_lists-1.0.1.dist-info/WHEEL
mdx_breakless_lists-1.0.1.dist-info/top_level.txt
mdx_breakless_lists-1.0.1.dist-info/RECORD
