Metadata-Version: 2.1
Name: mdx_breakless_lists
Version: 1.0.1
Summary: Python Markdown package extension to allow lists without a preceding empty line.
Home-page: https://github.com/adamb70/mdx-breakless-lists
Author: adamb70
License: MIT
Keywords: markdown extension,markdown,lists
Platform: UNKNOWN
Classifier: Intended Audience :: Developers
Classifier: Topic :: Text Processing :: Markup
Classifier: Topic :: Utilities
Classifier: Programming Language :: Python :: 3
Classifier: License :: OSI Approved :: MIT License
